{
  "date": "2026-07-02",
  "hour": "16",
  "total": 52,
  "fetched_at": "2026-07-02T16:01:09.614475+08:00",
  "news": [
    {
      "source": "CoinDesk",
      "title": "XRP edges higher as whale activity rises while retail traders stay cautious",
      "summary": "",
      "link": "https://www.coindesk.com/markets/2026/07/02/xrp-edges-higher-as-whale-activity-rises-while-retail-traders-stay-cautious",
      "published": "Thu, 02 Jul 2026 06:20:31 +0000"
    },
    {
      "source": "CoinDesk",
      "title": "Bitcoin's long-term holders have returned to accumulation",
      "summary": "",
      "link": "https://www.coindesk.com/markets/2026/07/02/bitcoin-long-term-holders-have-returned-to-accumulation",
      "published": "Thu, 02 Jul 2026 06:17:16 +0000"
    },
    {
      "source": "The Block",
      "title": "Avalanche Treasury stock plunges 73% since debut as company’s AVAX holdings lose value",
      "summary": "<p>At the end of the first quarter, the company's management raised 'substantial doubt' about its ability to continue operations.</p>",
      "link": "https://www.theblock.co/post/406990/avalanche-treasury-stock-plunge?utm_source=rss&utm_medium=rss",
      "published": "Thu, 02 Jul 2026 02:28:42 -0400"
    },
    {
      "source": "CoinTelegraph",
      "title": "Robinhood links with dYdX Labs to launch new DEX Arcus",
      "summary": "<p style=\"float: right; margin: 0 0 10px 15px; width: 240px;\"><img alt=\"Robinhood links with dYdX Labs to launch new DEX Arcus\" class=\"type:primaryImage\" src=\"https://s3-images.ctmedia.io/media/article-covers/hi-robinhood-how-the-fast-growing-stock-trading-app-got-into-crypto.jpg\" /></p><p>The crypto protocol dYdX has rebranded as Arcus and is joining Robinhood’s new blockchain to bring perpetual and tokenized stock trading. </p>",
      "link": "https://cointelegraph.com/news/robinhood-links-with-dydx-labs-to-launch-new-dex-arcus?utm_source=rss_feed&utm_medium=rss&utm_campaign=rss_partner_inbound",
      "published": "Thu, 02 Jul 2026 06:05:02 +0000"
    },
    {
      "source": "金色财经",
      "title": "谷歌在欧盟法院就41亿欧元安卓罚款案的诉讼中败诉",
      "summary": "【谷歌在欧盟法院就41亿欧元安卓罚款案的诉讼中败诉】金色财经报道，7月2日，谷歌与欧盟就41亿欧元(约合47亿美元)反垄断罚款的长期斗争最终以失败告终。欧盟最高法院周四裁定，监管机构对这家美国巨头滥用安卓系统市场支配地位的处罚是正确的。欧洲法院裁定，谷歌针对欧盟委员会处罚的上诉应予驳回。这一裁决具有法律约束力，对于该监管机构而言是一次重大胜利。自2018年首次开出罚单以来，欧盟一直在欧盟法院与谷歌进行诉讼。法院在一份关于该裁决的声明中表示：“驳回谷歌及其母公司Alphabet针对欧盟普通法院判决提出的上诉，从而确认了针对谷歌搜索在安卓操作系统领域滥用市场支配地位的处罚。”",
      "link": "https://jinse.com.cn/lives/520967.html",
      "published": "Thu, 02 Jul 2026 07:56:37 GMT"
    },
    {
      "source": "金色财经",
      "title": "经济学家：印尼通胀短期内可能走高",
      "summary": "【经济学家：印尼通胀短期内可能走高】金色财经报道，7月2日，Kenanga经济学家在一份报告中表示，预计印尼通胀短期内将走高。他们表示，食品和运输成本上涨，加上印尼盾持续疲软，可能会使价格压力保持在高位，尽管预计通胀将保持在印尼央行1.5%-3.5%的目标区间内。Kenanga将其对2026年印尼通胀的预测维持在3.1%，高于2025年的1.9%，但认为如果汇率继续承压，风险将偏向上行。该机构补充说，预计印尼央行将维持防御性政策立场，可能会再加息25个基点，以支撑印尼盾并遏制通胀。",
      "link": "https://jinse.com.cn/lives/520966.html",
      "published": "Thu, 02 Jul 2026 07:47:01 GMT"
    },
    {
      "source": "金色财经",
      "title": "瑞银下调下半年布油价格预测至每桶80美元",
      "summary": "【瑞银下调下半年布油价格预测至每桶80美元】金色财经报道，7月2日，瑞银将布伦特原油三季度和四季度价格预测下调至每桶80美元，将2027年布伦特原油均价预测下调至75美元/桶。近期美国与伊朗签署谅解备忘录及霍尔木兹海峡石油流动的增加促使该行下调近期油价预测。",
      "link": "https://jinse.com.cn/lives/520965.html",
      "published": "Thu, 02 Jul 2026 07:46:08 GMT"
    },
    {
      "source": "金色财经",
      "title": "F2Pool创始人Chun Wang向币安存入1.68万枚ETH和60枚WBTC",
      "summary": "【F2Pool创始人Chun Wang向币安存入1.68万枚ETH和60枚WBTC】金色财经报道，7月2日，据Onchain Lens监测，F2Pool创始人Chun Wang向Binance存入了1.6842万枚ETH（2687万美元）和60枚WBTC（361万美元）。自5月26日以来，其已从Binance累计提取9.1945万枚ETH（1.599亿美元）和973枚WBTC（6072万美元）。",
      "link": "https://jinse.com.cn/lives/520964.html",
      "published": "Thu, 02 Jul 2026 07:41:09 GMT"
    },
    {
      "source": "金色财经",
      "title": "软银集团旗下软银公司SB NEO将推出NeoCloud服务",
      "summary": "【软银集团旗下软银公司SB NEO将推出NeoCloud服务】金色财经报道，7月2日，软银集团旗下软银公司SB NEO将推出NeoCloud服务，为包括超大规模云厂商在内的美国大型企业提供大语言模型训练与推理所需的计算资源。",
      "link": "https://jinse.com.cn/lives/520963.html",
      "published": "Thu, 02 Jul 2026 07:37:41 GMT"
    },
    {
      "source": "金色财经",
      "title": "某巨鲸近两日累计增持并质押15,802枚ETH，价值约2500万美元",
      "summary": "【某巨鲸近两日累计增持并质押15,802枚ETH，价值约2500万美元】金色财经报道，7月2日，据Lookonchain监测，地址0x2684再次从Binance提取5,926枚ETH，价值约958万美元。过去两天内，该地址累计从Binance提取并质押15,802枚ETH，总价值约2500万美元。<p>原文链接: <a href=\"https://x.com/lookonchain/status/2072583474884784567\">https://x.com/lookonchain/status/2072583474884784567</a></p>",
      "link": "https://jinse.com.cn/lives/520962.html",
      "published": "Thu, 02 Jul 2026 07:32:25 GMT"
    },
    {
      "source": "金色财经",
      "title": "港股南方两倍做多海力士(07709.HK)跌超30%",
      "summary": "【港股南方两倍做多海力士(07709.HK)跌超30%】金色财经报道，港股南方两倍做多海力士(07709.HK)跌超30%。",
      "link": "https://jinse.com.cn/lives/520961.html",
      "published": "Thu, 02 Jul 2026 07:26:30 GMT"
    },
    {
      "source": "金色财经",
      "title": "机构：纽商所黄金期货或在每盎司4,000美元处获得支撑",
      "summary": "【机构：纽商所黄金期货或在每盎司4,000美元处获得支撑】金色财经报道，7月2日，RHB Retail Research的Joseph Chai在一份研究报告中表示，纽商所(Comex)黄金期货可能已在每盎司4,000美元处找到支撑。该分析师表示，日线图上最新向好的价格走势表明，第一支撑位已在该水平形成。Chai表示，鉴于这种贵金属似乎正在经历盘整，它可能会沿这一水平横盘整理。不过该分析师表示，20日和50日简单移动平均线均稳步走低，这可能会对该大宗商品造成下行压力。Chai补充说，上行方面，初步阻力位在每盎司4,400美元。",
      "link": "https://jinse.com.cn/lives/520960.html",
      "published": "Thu, 02 Jul 2026 07:24:13 GMT"
    },
    {
      "source": "金色财经",
      "title": "大摩上调高盛目标价至1099美元",
      "summary": "【大摩上调高盛目标价至1099美元】金色财经报道，7月2日，摩根士丹利将高盛的目标价从1021美元上调至1099美元，维持“持股观望”评级。(格隆汇)",
      "link": "https://jinse.com.cn/lives/520959.html",
      "published": "Thu, 02 Jul 2026 07:22:10 GMT"
    },
    {
      "source": "金色财经",
      "title": "商务部回应对美农产品关税问题",
      "summary": "【商务部回应对美农产品关税问题】金色财经报道，7月2日讯，商务部新闻发言人何亚东在7月2日举行的例行发布会上回应有关降低或取消对美国农产品关税的提问时说，农产品贸易是中美经贸合作的重要组成部分。经过近期经贸磋商，双方设定了扩大农产品双向贸易的指导性目标，并原则同意将相关农产品纳入对等降税框架安排。企业将遵循市场化原则，根据实际需求和市场条件自主开展贸易。中方愿与美方相向而行，为双向农产品贸易创造有利条件。（新华社）",
      "link": "https://jinse.com.cn/lives/520958.html",
      "published": "Thu, 02 Jul 2026 07:20:38 GMT"
    },
    {
      "source": "金色财经",
      "title": "Binance Alpha新空投积分门槛为至少226分",
      "summary": "【Binance Alpha新空投积分门槛为至少226分】金色财经报道，7月2日，Binance钱包发文宣布，请准备好领取Binance Alpha空投，并在今日10:00（UTC）进行交易。 \n本次活动采用更新的Binance Alpha Box模型，其中空投池包含来自多个项目的代币。持有至少226个Binance Alpha积分的用户可按先到先得的原则领取一个代币奖励。领取空投将消耗15个Binance Alpha积分。 \n此外，本次空投设有三个奖励等级：普通（奖励池的80%）、稀有（15%）和超级稀有（5%），每个等级对应不同的alphabox价值。领取时，用户将被分配到其中一个等级。奖励将按照这些等级比例进行分配。如果奖励未被完全领取，积分门槛将每5分钟自动降低5积分。",
      "link": "https://jinse.com.cn/lives/520957.html",
      "published": "Thu, 02 Jul 2026 07:17:38 GMT"
    },
    {
      "source": "金色财经",
      "title": "道富：黄金牛市周期仍有上升空间，未来6至9个月金价或高见5500美元",
      "summary": "【道富：黄金牛市周期仍有上升空间，未来6至9个月金价或高见5500美元】金色财经报道，7月2日，道富投资管理指出，尽管与2024至2025年比较，金价走势可能更动荡，但黄金牛市周期仍有上升空间，而美联储的鹰派政策转向，料不会改变疫情后黄金的结构性趋势。道富预期，未来6至9个月金价可能会涨至每盎司4750至5500美元，而金价在每盎司3750至4000美元有强劲支撑，但与1至2月的宏观环境相比，金价达到每盎司5500至6250美元的可能性较小。",
      "link": "https://jinse.com.cn/lives/520956.html",
      "published": "Thu, 02 Jul 2026 07:17:30 GMT"
    },
    {
      "source": "金色财经",
      "title": "花旗：维持小米“买入”评级及目标价37港元，估值相当具吸引力",
      "summary": "【花旗：维持小米“买入”评级及目标价37港元，估值相当具吸引力】金色财经报道，7月2日，花旗发表研报指，小米集团公布6月电动车交付量已超过3万辆。目前，YU7车型的交付周期基本保持稳定，基础版、长续航版、Pro、Max及GT车型均为6至9星期；而新SU7车型的交付周期则为4至7星期(相较于5月底基础版的8至11星期及Max版的10至13星期有所缩短)。该行指，目前该股交易在2026及2027年预测市盈率的18.8倍和13.6倍，估值相当具吸引力。该行预期，在对2026年的预期以及即将推出YU9的推动下，股价有望在8月迎来反弹；同时，若全球中国存储器厂商宣布更多资本支出而令存储器价格有见顶迹象，预料将在未来12个月内对小米股价带来正面影响。该行维持小米“买入”评级，目标价维持37港元不变。",
      "link": "https://jinse.com.cn/lives/520955.html",
      "published": "Thu, 02 Jul 2026 07:14:10 GMT"
    },
    {
      "source": "金色财经",
      "title": "科创50大跌超8%",
      "summary": "<figure><img alt=\"390\" src=\"https://img.jinse.com.cn/jinse_1782976296909627566_live-rb.png\" /></figure>【科创50大跌超8%】金色财经报道，7月2日，A股市场主要指数跌幅进一步扩大，其中，科创50大跌超8%，自2025年4月7日以来最大跌幅，创业板指跌超6%，深证成指跌超4%，沪深300跌超3%，上证50、全A、上证指数跌超2%。",
      "link": "https://jinse.com.cn/lives/520953.html",
      "published": "Thu, 02 Jul 2026 07:11:40 GMT"
    },
    {
      "source": "金色财经",
      "title": "巴克莱：国际足联世界杯招聘可能扭曲美国就业数据",
      "summary": "【巴克莱：国际足联世界杯招聘可能扭曲美国就业数据】金色财经报道，7月2日，巴克莱私人银行和财富管理公司的Julien Lafargue在一份报告中表示，美国6月份就业数据可能会因与国际足联世界杯相关的临时招聘而失真。该首席市场策略师表示：“数据也可能失真，因为与国际足联世界杯相关的招聘可能在调查期间暂时提振了休闲和酒店等行业的就业。“他表示，市场可能会更加看重7月14日发布的6月份CPI报告，因为通胀数据将提供对该国经济更清晰的解读。分析师预计，6月份将新增11.5万个就业岗位，较上个月的17.2万个有所放缓。",
      "link": "https://jinse.com.cn/lives/520952.html",
      "published": "Thu, 02 Jul 2026 07:08:42 GMT"
    },
    {
      "source": "金色财经",
      "title": "布伦特原油日内跌幅达1.00%，现报70.54美元/桶",
      "summary": "【布伦特原油日内跌幅达1.00%，现报70.54美元/桶】金色财经报道，7月2日，布伦特原油日内跌幅达1.00%，现报70.54美元/桶。(金十)",
      "link": "https://jinse.com.cn/lives/520951.html",
      "published": "Thu, 02 Jul 2026 07:08:30 GMT"
    },
    {
      "source": "金色财经",
      "title": "Binance将通过bStocks支持美光股票现金分红",
      "summary": "【Binance将通过bStocks支持美光股票现金分红】金色财经报道，7月2日，Binance将通过bStocks向美光股票持有者发放Micron(MU)现金股息。 \n扣除适用的预扣税、费用、成本和其他扣除项后，现金股息净额将再投资于同一基础证券的更多单位或部分份额。 \n符合条件的用户将以MUBb Stocks的形式收到股息。链上MUB持有者将通过乘数调整获得bStock分红。资格：在2026年7月6日00:00(UTC)的记录日快照中持有MUB的用户将有资格获得分红。",
      "link": "https://jinse.com.cn/lives/520950.html",
      "published": "Thu, 02 Jul 2026 07:03:36 GMT"
    },
    {
      "source": "金色财经",
      "title": "美元兑日元USD/JPY短线一度下挫超百点，最低触及161.13",
      "summary": "【美元兑日元USD/JPY短线一度下挫超百点，最低触及161.13】金色财经报道，7月2日，美元兑日元USD/JPY短线一度下挫超百点，最低触及161.13，随后反弹，现报161.7。(金十)",
      "link": "https://jinse.com.cn/lives/520949.html",
      "published": "Thu, 02 Jul 2026 06:54:33 GMT"
    },
    {
      "source": "金色财经",
      "title": "Metaplanet增持2,823枚BTC，总持仓量升至4.3万枚",
      "summary": "【Metaplanet增持2,823枚BTC，总持仓量升至4.3万枚】金色财经报道，7月2日，据官方披露，MetaPlanet宣布进一步增持2,823枚BTC，比特币持有量总计已达43,000枚。<p>原文链接: <a href=\"https://x.com/Metaplanet/status/2072569479024808222\">https://x.com/Metaplanet/status/2072569479024808222</a></p>",
      "link": "https://jinse.com.cn/lives/520948.html",
      "published": "Thu, 02 Jul 2026 06:45:31 GMT"
    },
    {
      "source": "金色财经",
      "title": "日韩股市周四收跌 韩股跌超7%",
      "summary": "【日韩股市周四收跌 韩股跌超7%】金色财经报道，7月2日，日经225指数7月2日（周四）收盘下跌1741.81点，跌幅2.47%，报68733.15点。韩国KOSPI指数7月2日（周四）收盘下跌655.32点，跌幅7.89%，报7648.09点，为6月8日以来最低收盘水平。(金十)",
      "link": "https://jinse.com.cn/lives/520947.html",
      "published": "Thu, 02 Jul 2026 06:37:23 GMT"
    },
    {
      "source": "Reuters Crypto",
      "title": "Trump reports over $1.4 billion in income from crypto ventures - Reuters",
      "summary": "<a href=\"https://news.google.com/rss/articles/CBMiXEFVX3lxTE9DWGFKdk1VbjNQbHFuRnNoX0ZhQTVBODJwUUpQUy03QjZGbEstTW55NlZVZUc4dDBhNnZYYmpsUVpLOGt2YXllSnVRR2pkUHlZVU1Ud3o1a1FGNHJT?oc=5\" target=\"_blank\">Trump reports over $1.4 billion in income from crypto ventures</a>&nbsp;&nbsp;<font color=\"#6f6f6f\">Reuters</font>",
      "link": "https://news.google.com/rss/articles/CBMiXEFVX3lxTE9DWGFKdk1VbjNQbHFuRnNoX0ZhQTVBODJwUUpQUy03QjZGbEstTW55NlZVZUc4dDBhNnZYYmpsUVpLOGt2YXllSnVRR2pkUHlZVU1Ud3o1a1FGNHJT?oc=5",
      "published": "Thu, 02 Jul 2026 07:08:44 GMT"
    },
    {
      "source": "CNBC Crypto",
      "title": "M&A is ‘on fire’ as large-cap firms simplify, Citi UK CEO says - CNBC",
      "summary": "<a href=\"https://news.google.com/rss/articles/CBMiaEFVX3lxTFB6aVlzdU9BdThoa254WWw5OE1oN0kxcWZjN1MzNHdVWXJHZ0QwQmVQVnNkVFhmeEtEYXVQdlJiT2ZGR1U4a2xTdUhTdExxS1NJdkprSDN0ZVBobTM0MllxM3FBdUVna2140gFuQVVfeXFMTlV4NGpKdU1uNmcxREpkdDZpT3paZjI3OFBLczVZd3NGY1A2UUVUZHVCVlNOdTJFOVpkUHpwWTdZUU9TRnJVeHVEZ0luUjd4eEZhTWVtREZFdElVUXp0YTl4N1BpQVlEa0RTMzlHZEE?oc=5\" target=\"_blank\">M&amp;A is ‘on fire’ as large-cap firms simplify, Citi UK CEO says</a>&nbsp;&nbsp;<font color=\"#6f6f6f\">CNBC</font>",
      "link": "https://news.google.com/rss/articles/CBMiaEFVX3lxTFB6aVlzdU9BdThoa254WWw5OE1oN0kxcWZjN1MzNHdVWXJHZ0QwQmVQVnNkVFhmeEtEYXVQdlJiT2ZGR1U4a2xTdUhTdExxS1NJdkprSDN0ZVBobTM0MllxM3FBdUVna2140gFuQVVfeXFMTlV4NGpKdU1uNmcxREpkdDZpT3paZjI3OFBLczVZd3NGY1A2UUVUZHVCVlNOdTJFOVpkUHpwWTdZUU9TRnJVeHVEZ0luUjd4eEZhTWVtREZFdElVUXp0YTl4N1BpQVlEa0RTMzlHZEE?oc=5",
      "published": "Thu, 02 Jul 2026 07:21:44 GMT"
    },
    {
      "source": "CNBC Crypto",
      "title": "Google loses legal fight over 4.1 billion-euro EU antitrust fine - CNBC",
      "summary": "<a href=\"https://news.google.com/rss/articles/CBMipAFBVV95cUxNMDgtdFV1YjNScWl5M2I4Y2ZwakxBMmVPUTFQd3BoclBjTk5xaXB6TUpjVU41VkxYR2JHYUtJS3p0ZlNiam5KUTJnV2o0UlNZckdFQlRldUc3b3BoWkFZNEdqdWVWZjloNk1kSzNIc0c1Q1pBaXdqNklsSUZXelZvZEpmczFaYnlsVGVUNlVqV1hWS1Q3aUtYWXBBWXZpeVhtQ19lRdIBqgFBVV95cUxOMW5LZlVidEJ6Z0tsSDg3bUZXMTFMU2JqTzFUeHdmSFJJaDFtMkxMTTFmcnlHeGFiMVdfWnJXREFEN0ptamhjdlhJX1B4UmQ3cElSWVVDcVBwSGY0VG1lZVU4ZHR3N0UtbDFMMUZ3b1Y0SU1mQ3p5MTdQQkw4UWE3eWhQRmhtTkRJcXlFWmQyOFhpLUhNQ0JEUUdlT1pId1E0Z3ducDlza2",
      "link": "https://news.google.com/rss/articles/CBMipAFBVV95cUxNMDgtdFV1YjNScWl5M2I4Y2ZwakxBMmVPUTFQd3BoclBjTk5xaXB6TUpjVU41VkxYR2JHYUtJS3p0ZlNiam5KUTJnV2o0UlNZckdFQlRldUc3b3BoWkFZNEdqdWVWZjloNk1kSzNIc0c1Q1pBaXdqNklsSUZXelZvZEpmczFaYnlsVGVUNlVqV1hWS1Q3aUtYWXBBWXZpeVhtQ19lRdIBqgFBVV95cUxOMW5LZlVidEJ6Z0tsSDg3bUZXMTFMU2JqTzFUeHdmSFJJaDFtMkxMTTFmcnlHeGFiMVdfWnJXREFEN0ptamhjdlhJX1B4UmQ3cElSWVVDcVBwSGY0VG1lZVU4ZHR3N0UtbDFMMUZ3b1Y0SU1mQ3p5MTdQQkw4UWE3eWhQRmhtTkRJcXlFWmQyOFhpLUhNQ0JEUUdlT1pId1E0Z3ducDlza2FKdw?oc=5",
      "published": "Thu, 02 Jul 2026 07:44:44 GMT"
    },
    {
      "source": "Reddit r/bitcoin",
      "title": "Daily Discussion, July 02, 2026",
      "summary": "<!-- SC_OFF --><div class=\"md\"><p>Please utilize this sticky thread for all general <strong>Bitcoin</strong> discussions! If you see posts on the front page or <a href=\"/r/Bitcoin/new\">/r/Bitcoin/new</a> which are better suited for this daily discussion thread, please help out by directing the OP to this thread instead. Thank you!</p> <p>If you don't get an answer to your question, you can try phrasing it differently or commenting again tomorrow.</p> <p>Please check the <a href=\"https://www.redd",
      "link": "https://www.reddit.com/r/Bitcoin/comments/1ul9voo/daily_discussion_july_02_2026/",
      "published": "2026-07-02T06:03:17+00:00"
    },
    {
      "source": "Reddit r/bitcoin",
      "title": "⚡ Lightning Thursday! July 02, 2026: Explore the Lightning Network!⚡",
      "summary": "<!-- SC_OFF --><div class=\"md\"><p>The lightning network is a second-layer solution on top of the Bitcoin blockchain that enables quick, cheap and scalable Bitcoin payments.</p> <p>Here is the place to discuss and learn more about lightning!</p> <p>Ask your questions about lightning</p> <p>Provide reviews, feedback, comparisons of LN apps, services, websites etc</p> <p>Learn about new LN features, development, apps</p> <p>Link to good quality resources (articles, wikis etc)</p> <p>Resources:</p>",
      "link": "https://www.reddit.com/r/Bitcoin/comments/1ulay3q/lightning_thursday_july_02_2026_explore_the/",
      "published": "2026-07-02T07:04:32+00:00"
    },
    {
      "source": "宏观经济",
      "title": "Fed expected to hold interest rates through 2026 amid inflation concerns - Crypto Briefing",
      "summary": "<a href=\"https://news.google.com/rss/articles/CBMiogFBVV95cUxNbzlWNENNeTAxN3FxY2VBcUFsRW1BdWdhaGdQY0ZNQVQ2a211TENwRm1fd2E3SDA2Y1h0UTJrN2hXaVhjd0lNMDhwVjh3QzY3ZUwtZ2ZucFk3b0VGdmxndTU4bG5yS002RjZma3kwZ2FRZEY4ZjBZUTUtWW1JN21oOXFaVlRjaWs1aDNPcFFLeGtEVldnclU0ODZQb2drMnQ1Q0E?oc=5\" target=\"_blank\">Fed expected to hold interest rates through 2026 amid inflation concerns</a>&nbsp;&nbsp;<font color=\"#6f6f6f\">Crypto Briefing</font>",
      "link": "https://news.google.com/rss/articles/CBMiogFBVV95cUxNbzlWNENNeTAxN3FxY2VBcUFsRW1BdWdhaGdQY0ZNQVQ2a211TENwRm1fd2E3SDA2Y1h0UTJrN2hXaVhjd0lNMDhwVjh3QzY3ZUwtZ2ZucFk3b0VGdmxndTU4bG5yS002RjZma3kwZ2FRZEY4ZjBZUTUtWW1JN21oOXFaVlRjaWs1aDNPcFFLeGtEVldnclU0ODZQb2drMnQ1Q0E?oc=5",
      "published": "Thu, 02 Jul 2026 06:19:00 GMT"
    },
    {
      "source": "宏观经济",
      "title": "US job growth slows in June as unemployment holds at 4.3%, and crypto markets are watching closely - Crypto Briefing",
      "summary": "<a href=\"https://news.google.com/rss/articles/CBMidEFVX3lxTE8xbkczdkZBLV9mUU9PaGhhalhjeUtEeTkxdW1ENllQWlpwMEV0U0FtbFVwZTFBM3U1aWN2Z1g3N0xPR2JnaXdRRjFLUHlkdU9yaFAtbjNYM3RIM3JobkdZWEZsdlZucjdiYjF2RDJwSk9DRHZH?oc=5\" target=\"_blank\">US job growth slows in June as unemployment holds at 4.3%, and crypto markets are watching closely</a>&nbsp;&nbsp;<font color=\"#6f6f6f\">Crypto Briefing</font>",
      "link": "https://news.google.com/rss/articles/CBMidEFVX3lxTE8xbkczdkZBLV9mUU9PaGhhalhjeUtEeTkxdW1ENllQWlpwMEV0U0FtbFVwZTFBM3U1aWN2Z1g3N0xPR2JnaXdRRjFLUHlkdU9yaFAtbjNYM3RIM3JobkdZWEZsdlZucjdiYjF2RDJwSk9DRHZH?oc=5",
      "published": "Thu, 02 Jul 2026 06:57:46 GMT"
    },
    {
      "source": "Binance公告",
      "title": "Binance Will Add Gram (GRAM) on Earn, Buy Crypto, Convert, VIP Loan, Margin & Futures",
      "summary": "Binance Will Add Gram (GRAM) on Earn, Buy Crypto, Convert, VIP Loan, Margin & Futures",
      "link": "https://www.binance.com/zh-CN/support/announcement/3da0bd5b07bf497db5788fed38d478b0",
      "published": "2026-07-02T15:45:17.244000+08:00"
    },
    {
      "source": "Binance公告",
      "title": "Binance Futures Will Launch USDⓈ-Margined BTCU and ETHU Perpetual Contracts (2026-07-01)",
      "summary": "Binance Futures Will Launch USDⓈ-Margined BTCU and ETHU Perpetual Contracts (2026-07-01)",
      "link": "https://www.binance.com/zh-CN/support/announcement/25da4614ffff435fa28544b27fd33a39",
      "published": "2026-06-30T22:45:02.782000+08:00"
    },
    {
      "source": "Binance公告",
      "title": "Binance Exchange Adds bStocks Lumentum (LITEB), Meta (METAB), Microsoft (MSFTB), Palantir (PLTRB) and Invesco QQQ Trust (QQQB) Trading Pair(s) on Binance Spot - 2026-06-30",
      "summary": "Binance Exchange Adds bStocks Lumentum (LITEB), Meta (METAB), Microsoft (MSFTB), Palantir (PLTRB) and Invesco QQQ Trust (QQQB) Trading Pair(s) on Binance Spot - 2026-06-30",
      "link": "https://www.binance.com/zh-CN/support/announcement/03b264b679a646119d1a2415b9097bd6",
      "published": "2026-06-30T13:30:25.419000+08:00"
    },
    {
      "source": "Binance公告",
      "title": "Introducing OpenGradient (OPG) on Binance HODLer Airdrops! Earn OPG With Retroactive BNB Simple Earn Subscriptions",
      "summary": "Introducing OpenGradient (OPG) on Binance HODLer Airdrops! Earn OPG With Retroactive BNB Simple Earn Subscriptions",
      "link": "https://www.binance.com/zh-CN/support/announcement/b026c9829d28459cb1f1a95000960a08",
      "published": "2026-06-30T13:00:03.128000+08:00"
    },
    {
      "source": "Binance公告",
      "title": "Binance Margin Will Add New Pairs - 2026-06-30",
      "summary": "Binance Margin Will Add New Pairs - 2026-06-30",
      "link": "https://www.binance.com/zh-CN/support/announcement/d8400c84767448a2bcb71b7bf3864a97",
      "published": "2026-06-30T12:30:19.411000+08:00"
    },
    {
      "source": "Binance公告",
      "title": "Notice on New Trading Pairs & Trading Bots Services on Binance Spot - 2026-06-30",
      "summary": "Notice on New Trading Pairs & Trading Bots Services on Binance Spot - 2026-06-30",
      "link": "https://www.binance.com/zh-CN/support/announcement/8057e105f5724d9bbf29ba416f14149e",
      "published": "2026-06-29T17:30:03.090000+08:00"
    },
    {
      "source": "Binance公告",
      "title": "Binance Futures Will Launch USDⓈ-Margined CAPUSDT Perpetual Contract (2026-06-27)",
      "summary": "Binance Futures Will Launch USDⓈ-Margined CAPUSDT Perpetual Contract (2026-06-27)",
      "link": "https://www.binance.com/zh-CN/support/announcement/a444dd2f67da43e0bafdd730fddc3887",
      "published": "2026-06-27T18:50:43.165000+08:00"
    },
    {
      "source": "Binance公告",
      "title": "Binance Futures Will Launch USDⓈ-Margined OUSDT Perpetual Contract (2026-06-24)",
      "summary": "Binance Futures Will Launch USDⓈ-Margined OUSDT Perpetual Contract (2026-06-24)",
      "link": "https://www.binance.com/zh-CN/support/announcement/a6b7d5a8a14a44c1b6a6a34813c6d93f",
      "published": "2026-06-24T18:30:18.531000+08:00"
    },
    {
      "source": "Binance公告",
      "title": "Binance Futures Will Launch Multiple USDⓈ-Margined TradFi Perpetual Contracts (2026-06-29)",
      "summary": "Binance Futures Will Launch Multiple USDⓈ-Margined TradFi Perpetual Contracts (2026-06-29)",
      "link": "https://www.binance.com/zh-CN/support/announcement/ba04ce1272df4bdf8d2595ccb0e1954b",
      "published": "2026-06-23T18:00:31.403000+08:00"
    },
    {
      "source": "Binance公告",
      "title": "Binance Adds New JPY Spot Trading Pairs and Launches Zero Maker Fee Promotion - 2026-06-26",
      "summary": "Binance Adds New JPY Spot Trading Pairs and Launches Zero Maker Fee Promotion - 2026-06-26",
      "link": "https://www.binance.com/zh-CN/support/announcement/d83363b157b24be699c47baa4aa307fa",
      "published": "2026-06-23T16:15:03.419000+08:00"
    },
    {
      "source": "Binance公告",
      "title": "Binance Margin Will Add New Pairs - 2026-06-23",
      "summary": "Binance Margin Will Add New Pairs - 2026-06-23",
      "link": "https://www.binance.com/zh-CN/support/announcement/3af18ad98b3048a3b959ef1405b9d45b",
      "published": "2026-06-23T15:00:02.113000+08:00"
    },
    {
      "source": "Binance公告",
      "title": "Binance Exchange Adds bStocks Advanced Micro Devices (AMDB), iShares MSCI South Korea ETF (EWYB), Intel (INTCB) and Strategy (MSTRB) Trading Pair(s) on Binance Spot - 2026-06-23",
      "summary": "Binance Exchange Adds bStocks Advanced Micro Devices (AMDB), iShares MSCI South Korea ETF (EWYB), Intel (INTCB) and Strategy (MSTRB) Trading Pair(s) on Binance Spot - 2026-06-23",
      "link": "https://www.binance.com/zh-CN/support/announcement/d1343e10bc2648cd8302c83a5b1223a9",
      "published": "2026-06-23T14:32:00.591000+08:00"
    },
    {
      "source": "Binance公告",
      "title": "Binance Futures Will Launch USDⓈ-Margined ARXUSDT Perpetual Contract (2026-06-23)",
      "summary": "Binance Futures Will Launch USDⓈ-Margined ARXUSDT Perpetual Contract (2026-06-23)",
      "link": "https://www.binance.com/zh-CN/support/announcement/7fa4e8b3ced94b4c8c189a4593dbce9b",
      "published": "2026-06-23T11:30:38.167000+08:00"
    },
    {
      "source": "Binance公告",
      "title": "Binance Futures Will Launch Multiple USDⓈ-Margined TradFi Perpetual Contracts (2026-06-22)",
      "summary": "Binance Futures Will Launch Multiple USDⓈ-Margined TradFi Perpetual Contracts (2026-06-22)",
      "link": "https://www.binance.com/zh-CN/support/announcement/88ea4a4f9f0b4ad4b7b308195c026fe4",
      "published": "2026-06-22T16:15:20.368000+08:00"
    },
    {
      "source": "Binance公告",
      "title": "Notice on New Trading Pairs & Trading Bots Services on Binance Spot - 2026-06-23",
      "summary": "Notice on New Trading Pairs & Trading Bots Services on Binance Spot - 2026-06-23",
      "link": "https://www.binance.com/zh-CN/support/announcement/f0c763fc49934c1b9b4e4ce1653e67dc",
      "published": "2026-06-22T14:00:02.890000+08:00"
    },
    {
      "source": "Binance公告",
      "title": "Binance Will Add Re (RE) on Earn, Buy Crypto, Convert, VIP Loan, Margin & Futures",
      "summary": "Binance Will Add Re (RE) on Earn, Buy Crypto, Convert, VIP Loan, Margin & Futures",
      "link": "https://www.binance.com/zh-CN/support/announcement/005d1ef77538417cbe69d4703deb1969",
      "published": "2026-06-18T21:45:04.798000+08:00"
    },
    {
      "source": "Binance公告",
      "title": "Binance Will List Re (RE) with Seed Tag Applied",
      "summary": "Binance Will List Re (RE) with Seed Tag Applied",
      "link": "https://www.binance.com/zh-CN/support/announcement/4f90bec2f7984f71aaa9465830b1c6a6",
      "published": "2026-06-18T17:47:21.424000+08:00"
    },
    {
      "source": "Binance公告",
      "title": "Binance Futures Will List USDⓈ-M & COIN-M Quarterly 1225 Delivery Contracts",
      "summary": "Binance Futures Will List USDⓈ-M & COIN-M Quarterly 1225 Delivery Contracts",
      "link": "https://www.binance.com/zh-CN/support/announcement/81092181ec124efea616f591cf335c05",
      "published": "2026-06-18T10:00:33.640000+08:00"
    },
    {
      "source": "Binance公告",
      "title": "Binance Exchange Adds bStocks Tokenized Securities SpaceX (SPCXB) on Binance Spot - 2026-06-12",
      "summary": "Binance Exchange Adds bStocks Tokenized Securities SpaceX (SPCXB) on Binance Spot - 2026-06-12",
      "link": "https://www.binance.com/zh-CN/support/announcement/191cb96109f24c5c85362631a55a45d3",
      "published": "2026-06-13T00:00:00.917000+08:00"
    },
    {
      "source": "Binance公告",
      "title": "Binance Exchange Adds bStocks Tokenized Securities Trading Pair(s) & Trading Bots Services on Binance Spot - 2026-06-11",
      "summary": "Binance Exchange Adds bStocks Tokenized Securities Trading Pair(s) & Trading Bots Services on Binance Spot - 2026-06-11",
      "link": "https://www.binance.com/zh-CN/support/announcement/5646e3f9ea6b4c989cb76aa18bd99245",
      "published": "2026-06-11T22:05:06.698000+08:00"
    },
    {
      "source": "Fear & Greed Index",
      "title": "恐惧贪婪指数: 19 (Extreme Fear)",
      "summary": "当前加密市场恐惧贪婪指数为 19，分类为「Extreme Fear」。 市场处于极度恐惧状态，历史上往往是抄底机会。",
      "link": "https://alternative.me/crypto/fear-and-greed-index/",
      "published": "2026-07-02T08:00:00+08:00"
    }
  ]
}