{
  "date": "2026-06-24",
  "hour": "00",
  "news": [
    {
      "title": "Chainlink与47家韩欧银行合作",
      "summary": "Chainlink与47家韩国和欧洲银行组成联盟，共同开发基于区块链的国际汇款结算网络，旨在提高跨境支付效率。这一合作将增强Chainlink在传统金融领域的应用，有望推动LINK代币的采用和价格上涨。属于项目重大更新的看多信号。",
      "reason": "与传统银行大规模合作是项目更新的重大利好，影响中期行情。",
      "category": "项目更新",
      "impact_coins": [
        "LINK"
      ],
      "signal": "bullish",
      "impact_level": 3,
      "sources": [
        {
          "name": "CoinDesk",
          "url": "https://www.coindesk.com/markets/2026/06/23/chainlink-teams-up-with-47-south-korean-european-banks-to-speed-up-international-money-transfers"
        },
        {
          "name": "CoinTelegraph",
          "url": "https://cointelegraph.com/news/chainlink-europe-korea-banks-stablecoin-fx-settlement-project-pangea"
        }
      ],
      "urgency": "days"
    },
    {
      "title": "Tether支持的Oobit将USDT接入巴西PIX",
      "summary": "Tether投资的支付平台Oobit与巴西PIX支付网络整合，使近1.7亿巴西用户可以直接使用USDT进行支付。这大幅扩展了USDT的使用场景，有利于稳定币需求增长，间接利好整个加密货币市场。属于稳定币采用的重要里程碑，看多信号。",
      "reason": "稳定币在重要经济体的支付集成将增加其使用量，可能带动资金流入，符合优先级一。",
      "category": "项目更新",
      "impact_coins": [
        "USDT"
      ],
      "signal": "bullish",
      "impact_level": 2,
      "sources": [
        {
          "name": "The Block",
          "url": "https://www.theblock.co/post/405819/tether-backed-oobit-brings-usdt-170-million-users-brazils-pix-payment-network"
        }
      ],
      "urgency": "hours"
    },
    {
      "title": "Apple威胁下架Sparrow比特币钱包",
      "summary": "Apple向比特币钱包Sparrow开发者发出App Store下架威胁，原因是其涉及未批准的加密货币功能。此举可能限制iOS用户使用比特币钱包，对BTC的日常使用和采用构成轻微负面影响，属于利空信号，但影响有限。",
      "reason": "科技巨头限制比特币钱包可能影响采用，但事件级别较低，符合市场情绪分类。",
      "category": "市场情绪",
      "impact_coins": [
        "BTC"
      ],
      "signal": "bearish",
      "impact_level": 2,
      "sources": [
        {
          "name": "Reddit r/cryptocurrency",
          "url": "https://www.reddit.com/r/CryptoCurrency/comments/1uditv7/apple_threatens_sparrow_bitcoin_wallet_dev_with/"
        }
      ],
      "urgency": "days"
    }
  ],
  "total_fetched": 50,
  "generated_at": "2026-06-24T00:01:48.639859+08:00"
}