{
  "date": "2026-05-19",
  "hour": "13",
  "news": [
    {
      "title": "SEC拟推代币化股票框架",
      "summary": "据彭博社报道，美国证券交易委员会（SEC）最早可能于本周提出代币化股票的创新豁免框架，允许华尔街机构交易代币化股票。此举将显著降低代币化资产的监管不确定性，可能推动RWA（真实世界资产）赛道的合规发展。受影响的币种包括POLYX、ONDO等代币化资产相关代币，以及整体市场情绪。看多信号，因为合规框架将吸引更多机构资金入场。",
      "reason": "优先级一：重大监管动态，直接影响代币化资产赛道，市场情绪利好。",
      "category": "监管政策",
      "impact_coins": [
        "POLYX",
        "ONDO",
        "BTC",
        "ETH"
      ],
      "signal": "bullish",
      "impact_level": 4,
      "sources": [
        {
          "name": "CoinDesk",
          "url": "https://www.coindesk.com/policy/2026/05/19/sec-to-propose-tokenized-stock-framework-as-wall-street-efforts-deepen-bloomberg/"
        },
        {
          "name": "Bloomberg",
          "url": "https://www.bloomberg.com/news/articles/2026-05-19/sec-readying-plan-for-trading-crypto-versions-of-stocks"
        }
      ],
      "urgency": "immediate"
    },
    {
      "title": "Warsh周五宣誓就任美联储主席",
      "summary": "Kevin M. Warsh将于本周五宣誓就任美联储新主席，接替鲍威尔。市场关注其货币政策立场，Warsh被视为偏鹰派，但具体政策方向仍不确定。短期内可能增加市场波动，历史数据显示美联储主席更迭期间风险资产通常承压。对加密货币的影响中性偏空，因不确定性上升。",
      "reason": "优先级二：宏观经济事件，美联储主席更迭影响利率预期和风险资产。",
      "category": "宏观经济",
      "impact_coins": [
        "BTC",
        "ETH"
      ],
      "signal": "neutral",
      "impact_level": 3,
      "sources": [
        {
          "name": "Crypto Briefing",
          "url": "https://news.google.com/rss/articles/CBMiakFVX3lxTE1UeS13N1lfbUQ5UWlNRHJPUDR5Y0swNnB2REIzcnRTd3hDa0c5alZUaFlRamxvSVY5MGJENlFNY1I2MWJOTnlFTXRNU3k5S19UbWp5eEF1cms1SEl3UmcySmFEYXV2Tk1GOWc?oc=5"
        }
      ],
      "urgency": "hours"
    },
    {
      "title": "Echo协议遭攻击，黑客铸造1000 eBTC",
      "summary": "Monad链上的BTCFi协议Echo被攻击，黑客通过漏洞铸造了1000枚eBTC并部分转入Tornado Cash。平台已暂停所有跨链交易。该事件直接冲击eBTC及Monad生态，短期抛压风险上升。同时可能引发对BTCFi协议的信任危机。看空eBTC和Monad链上资产。",
      "reason": "优先级一：项目方重大安全事件，黑客攻击导致直接损失和恐慌。",
      "category": "项目更新",
      "impact_coins": [
        "eBTC",
        "MONAD"
      ],
      "signal": "bearish",
      "impact_level": 4,
      "sources": [
        {
          "name": "The Block",
          "url": "https://www.theblock.co/post/401775/echo-exploit-ebtc-monad"
        },
        {
          "name": "金色财经",
          "url": "https://www.jinse.com/news/blockchain/...（原文链接）"
        }
      ],
      "urgency": "immediate"
    }
  ],
  "total_fetched": 23,
  "generated_at": "2026-05-19T13:01:43.716478+08:00"
}