{
  "date": "2026-05-09",
  "hour": "11",
  "news": [
    {
      "title": "Binance上线BILL合约",
      "summary": "Binance Futures将于2026-05-07上线BILLUSDT永续合约，提供最高75倍杠杆。BILL是某个迷因币或项目代币，合约上线通常会增加交易量和波动，但方向不确定。短期看多合约交易量，对现货价格有正向影响。偏多信号。",
      "reason": "新合约上线增加交易机会，可能带动价格波动。",
      "category": "交易所",
      "impact_coins": [
        "BILL"
      ],
      "signal": "bullish",
      "impact_level": 2,
      "sources": [
        {
          "name": "Binance",
          "url": "https://www.binance.com/zh-CN/support/announcement/7220be8100ee41149169e9179c380c8c"
        }
      ],
      "urgency": "hours"
    }
  ],
  "total_fetched": 26,
  "generated_at": "2026-05-09T11:03:06.976854+08:00"
}