{
  "date": "2026-06-27",
  "hour": "17",
  "news": [
    {
      "title": "EU议员要求评估DeFi监管",
      "summary": "欧盟立法者呼吁评估DeFi、质押和NFT的监管框架，可能出台新规。若监管收紧，对DeFi项目（如UNI、AAVE）不利，但合规项目受益。短期中性偏空，长期需关注具体法规。",
      "reason": "监管政策优先级高，可能影响DeFi板块中期走势。",
      "category": "监管政策",
      "impact_coins": [
        "UNI",
        "AAVE",
        "ETH"
      ],
      "signal": "bearish",
      "impact_level": 3,
      "sources": [
        {
          "name": "CoinTelegraph",
          "url": "https://cointelegraph.com/news/eu-lawmakers-assessing-defi-staking-nft-regulation"
        }
      ],
      "urgency": "days"
    }
  ],
  "total_fetched": 30,
  "generated_at": "2026-06-27T17:01:53.290334+08:00"
}